[{
  "id": 1,
  "name": "hero Product",
  "disc": "Lorem ipsum dolor sit amet",
  "price": "99",
  "color": "#33505a",
  "image": "http://placehold.it/940x300/999/CCC"
},{
  "id": 2,
  "name": "hero Product",
  "disc": "Lorem ipsum dolor sit amet",
  "price": "99",
  "color": "#33505a",
  "image": "http://placehold.it/940x300/999/CCC"
},{
  "id": 3,
  "name": "hero Product",
  "disc": "Lorem ipsum dolor sit amet",
  "price": "99",
  "color": "#33505a",
  "image": "http://placehold.it/940x300/999/CCC"
},{
  "id": 4,
  "name": "hero Product",
  "disc": "Lorem ipsum dolor sit amet",
  "price": "99",
  "color": "#33505a",
  "image": "http://placehold.it/940x300/999/CCC"
},{
  "id": 5,
  "name": "hero Product",
  "disc": "Lorem ipsum dolor sit amet",
  "price": "99",
  "color": "#33505a",
  "image": "http://placehold.it/940x300/999/CCC"
}
]